nonebot_plugin_yaoyang/__init__.py
nonebot_plugin_yaoyang/resource/guaa.mp3
nonebot_plugin_yaoyang/resource/不再低调.mp3
nonebot_plugin_yaoyang/resource/不要.mp3
nonebot_plugin_yaoyang/resource/不要叫了.mp3
nonebot_plugin_yaoyang/resource/不要吵.mp3
nonebot_plugin_yaoyang/resource/不要吵2.mp3
nonebot_plugin_yaoyang/resource/东星耀扬.mp3
nonebot_plugin_yaoyang/resource/为非作歹.mp3
nonebot_plugin_yaoyang/resource/亚洲捆绑.mp3
nonebot_plugin_yaoyang/resource/什么声音.mp3
nonebot_plugin_yaoyang/resource/你他妈干嘛.mp3
nonebot_plugin_yaoyang/resource/你以为.mp3
nonebot_plugin_yaoyang/resource/你在搞神马.mp3
nonebot_plugin_yaoyang/resource/凤舞九天.mp3
nonebot_plugin_yaoyang/resource/击飞.mp3
nonebot_plugin_yaoyang/resource/别.mp3
nonebot_plugin_yaoyang/resource/别搞我好吗.mp3
nonebot_plugin_yaoyang/resource/功亏一篑.mp3
nonebot_plugin_yaoyang/resource/史册.mp3
nonebot_plugin_yaoyang/resource/告白气球.mp3
nonebot_plugin_yaoyang/resource/哇靠.mp3
nonebot_plugin_yaoyang/resource/哦.mp3
nonebot_plugin_yaoyang/resource/啊.mp3
nonebot_plugin_yaoyang/resource/嘤嘤嘤.mp3
nonebot_plugin_yaoyang/resource/嘿.mp3
nonebot_plugin_yaoyang/resource/大胆.mp3
nonebot_plugin_yaoyang/resource/好了别狗叫啦.mp3
nonebot_plugin_yaoyang/resource/威慑.mp3
nonebot_plugin_yaoyang/resource/宫保鸡丁.mp3
nonebot_plugin_yaoyang/resource/小试牛刀.mp3
nonebot_plugin_yaoyang/resource/心烦意乱.mp3
nonebot_plugin_yaoyang/resource/我是主播.mp3
nonebot_plugin_yaoyang/resource/护驾.mp3
nonebot_plugin_yaoyang/resource/护驾护驾.mp3
nonebot_plugin_yaoyang/resource/拉扯.mp3
nonebot_plugin_yaoyang/resource/搞乱了.mp3
nonebot_plugin_yaoyang/resource/摆头.mp3
nonebot_plugin_yaoyang/resource/摆头走位.mp3
nonebot_plugin_yaoyang/resource/收不收.mp3
nonebot_plugin_yaoyang/resource/放我一马.mp3
nonebot_plugin_yaoyang/resource/旺旺狗.mp3
nonebot_plugin_yaoyang/resource/本座来也.mp3
nonebot_plugin_yaoyang/resource/杂鱼.mp3
nonebot_plugin_yaoyang/resource/来搞我.mp3
nonebot_plugin_yaoyang/resource/江南.mp3
nonebot_plugin_yaoyang/resource/狗叫什么.mp3
nonebot_plugin_yaoyang/resource/瓜皮.mp3
nonebot_plugin_yaoyang/resource/砸键盘.mp3
nonebot_plugin_yaoyang-0.1.4.dist-info/METADATA
nonebot_plugin_yaoyang-0.1.4.dist-info/WHEEL
nonebot_plugin_yaoyang-0.1.4.dist-info/RECORD
