Metadata-Version: 2.1
Name: nonebot_plugin_yaoyang
Version: 0.1.4
Summary: 发送耀阳语音
License: MIT
Author: Endless-Path
Author-email: rk.chensiyu@gmail.com
Requires-Python: >=3.10,<4.0
Classifier: License :: OSI Approved :: MIT License
Classifier: Programming Language :: Python :: 3
Classifier: Programming Language :: Python :: 3.10
Classifier: Programming Language :: Python :: 3.11
Classifier: Programming Language :: Python :: 3.12
Classifier: Programming Language :: Python :: 3.13
Requires-Dist: nonebot-adapter-onebot (>=2.3.0,<3.0.0)
Requires-Dist: nonebot2 (>=2.2.0,<3.0.0)
